pexcard/__init__.py
pexcard/error.py
pexcard/pex.py
pexcard/test_pex.py
pexcard-0.1.13.dist-info/DESCRIPTION.rst
pexcard-0.1.13.dist-info/METADATA
pexcard-0.1.13.dist-info/metadata.json
pexcard-0.1.13.dist-info/RECORD
pexcard-0.1.13.dist-info/top_level.txt
pexcard-0.1.13.dist-info/WHEEL
