Metadata-Version: 2.0
Name: pexcard
Version: 0.1.13
Summary: Python library for the PEX Card v4 API
Home-page: https://github.com/postmates/pex-api-wrapper
Author: Danyal Anik, Weixin Liu, Salar Khan
Author-email: danyal@postmates.com, frank@postmates.com, salar@postmates.com
License: MIT
Download-URL: https://github.com/postmates/pex-api-wrapper/mypackage/tarball/0.4
Platform: UNKNOWN
